[
  {"title":"JavaScriptをOCamlから生成するトランスパイラ「BuckleScript 1.0」、米ブルームバーグがオープンソースで公開。TypeScriptよりタイプセーフかつ効率的で高速と － Publickey","url":"http://www.publickey1.jp/blog/16/javascriptocamlbucklescript_10.html","description":"","label":"ocaml,altjs","createdAt":1473064259995},
  {"title":"Facebook、新しいMySQL用ストレージエンジン「MyRocks」をオープンソースで公開。フラッシュに適したデータの書き込みと圧縮効果 － Publickey","url":"http://www.publickey1.jp/blog/16/facebookmysqlmyrocks.html","description":"","label":"mysql,db,facebook","createdAt":1473064720255},
  {"title":"TLS徹底演習 // Speaker Deck","url":"https://speakerdeck.com/shigeki/tlsche-di-yan-xi","description":"","label":"","createdAt":1473775271526},
  {"title":"React Fiberアーキテクチャについて | プログラミング | POSTD","url":"http://postd.cc/react-fiber-architecture/","description":"","label":"","createdAt":1473775320102},
  {"title":"マイクロサービスの終焉 | 開発手法・プロジェクト管理 | POSTD","url":"http://postd.cc/the-end-of-microservices/","description":"","label":"","createdAt":1473775345925},
  {"title":"知っているようで意外と知らない、DDoSの基礎知識 - Qiita","url":"http://qiita.com/ueyasu/items/064839f9289c3db63c26","description":"","label":"security","createdAt":1473898965092},
  {"title":"Angular, version 2: proprioception-reinforcement","url":"http://angularjs.blogspot.jp/2016/09/angular2-final.html","description":"","label":"","createdAt":1473909862279}
]
